ipypandas/__init__.py
ipypandas/version.py
ipypandas/widget.py
ipypandas/labextension/package.json
ipypandas/labextension/static/100.71f6affc650afcc3e14a.js
ipypandas/labextension/static/100.71f6affc650afcc3e14a.js.LICENSE.txt
ipypandas/labextension/static/122.589ada189966d8ae7abb.js
ipypandas/labextension/static/509.f920516321e4eabd4d25.js
ipypandas/labextension/static/689.12594ad1d14917e4bb23.js
ipypandas/labextension/static/885.fa020a3d17cf559c8b6a.js
ipypandas/labextension/static/remoteEntry.ce44ee54d249cc307b34.js
ipypandas/labextension/static/style.js
ipypandas/labextension/static/third-party-licenses.json
ipypandas/nbextension/extension.js
ipypandas/nbextension/index.js
ipypandas/nbextension/index.js.LICENSE.txt
ipypandas/nbextension/index.js.map
ipypandas-0.1.0.data/data/share/jupyter/labextensions/ipypandas/package.json
ipypandas-0.1.0.data/data/share/jupyter/labextensions/ipypandas/static/100.71f6affc650afcc3e14a.js
ipypandas-0.1.0.data/data/share/jupyter/labextensions/ipypandas/static/100.71f6affc650afcc3e14a.js.LICENSE.txt
ipypandas-0.1.0.data/data/share/jupyter/labextensions/ipypandas/static/122.589ada189966d8ae7abb.js
ipypandas-0.1.0.data/data/share/jupyter/labextensions/ipypandas/static/509.f920516321e4eabd4d25.js
ipypandas-0.1.0.data/data/share/jupyter/labextensions/ipypandas/static/689.12594ad1d14917e4bb23.js
ipypandas-0.1.0.data/data/share/jupyter/labextensions/ipypandas/static/885.fa020a3d17cf559c8b6a.js
ipypandas-0.1.0.data/data/share/jupyter/labextensions/ipypandas/static/remoteEntry.ce44ee54d249cc307b34.js
ipypandas-0.1.0.data/data/share/jupyter/labextensions/ipypandas/static/style.js
ipypandas-0.1.0.data/data/share/jupyter/labextensions/ipypandas/static/third-party-licenses.json
ipypandas-0.1.0.data/data/share/jupyter/nbextensions/ipypandas/extension.js
ipypandas-0.1.0.data/data/share/jupyter/nbextensions/ipypandas/index.js
ipypandas-0.1.0.data/data/share/jupyter/nbextensions/ipypandas/index.js.LICENSE.txt
ipypandas-0.1.0.dist-info/METADATA
ipypandas-0.1.0.dist-info/WHEEL
ipypandas-0.1.0.dist-info/licenses/LICENSE
ipypandas-0.1.0.dist-info/RECORD
