Metadata-Version: 2.1
Name: ipypandas
Version: 0.1.0
Summary: Interactive features for the python data analysis library pandas in jupyter.
Project-URL: Homepage, https://twa.re/ipypandas
Project-URL: Repository, https://github.com/tensorware/ipypandas
Author: Tensorware
License: Copyright (c) 2024 Tensorware.
License-File: LICENSE
Keywords: IPython,Jupyter,Widgets
Classifier: Framework :: Jupyter :: JupyterLab
Classifier: Framework :: Jupyter :: JupyterLab :: Extensions
Classifier: Intended Audience :: Developers
Classifier: Intended Audience :: Science/Research
Classifier: License :: OSI Approved :: BSD License
Classifier: Programming Language :: Python
Classifier: Programming Language :: Python :: 3
Classifier: Programming Language :: Python :: 3.8
Classifier: Programming Language :: Python :: 3.9
Classifier: Programming Language :: Python :: 3.10
Classifier: Programming Language :: Python :: 3.11
Classifier: Programming Language :: Python :: 3.12
Requires-Python: >=3.8
Requires-Dist: ipywidgets>=8.0.0
Requires-Dist: pandas>=2.0.0
Provides-Extra: build
Requires-Dist: hatch>=1.9.3; extra == 'build'
Requires-Dist: tbump>=6.8.0; extra == 'build'
Provides-Extra: dev
Requires-Dist: ipypandas[build,docs,examples,tests]; extra == 'dev'
Provides-Extra: docs
Requires-Dist: jupyter-sphinx>=0.4.0; extra == 'docs'
Requires-Dist: nbsphinx-link>=1.3.0; extra == 'docs'
Requires-Dist: nbsphinx>=0.8.10; extra == 'docs'
Requires-Dist: pydata-sphinx-theme>=0.8.0; extra == 'docs'
Requires-Dist: pypandoc>=1.7.5; extra == 'docs'
Requires-Dist: pytest-check-links>=0.7.0; extra == 'docs'
Requires-Dist: sphinx>=5.0.0; extra == 'docs'
Provides-Extra: examples
Requires-Dist: ipywidgets>=8.0.0; extra == 'examples'
Requires-Dist: jupyterlab>=4.0.0; extra == 'examples'
Requires-Dist: matplotlib>=3.0.0; extra == 'examples'
Requires-Dist: pandas>=2.0.0; extra == 'examples'
Requires-Dist: pyarrow>=15.0.0; extra == 'examples'
Provides-Extra: tests
Requires-Dist: nbval>=0.9.5; extra == 'tests'
Requires-Dist: pytest>=7.0.0; extra == 'tests'
